MANIFEST.in
README.md
README.rst
requirements.txt
setup.py
wva/__init__.py
wva/cli.py
wva/core.py
wva/exceptions.py
wva/grapher.py
wva/http_client.py
wva/stream.py
wva/subscriptions.py
wva/vehicle.py
wva/version.py
wva.egg-info/PKG-INFO
wva.egg-info/SOURCES.txt
wva.egg-info/dependency_links.txt
wva.egg-info/entry_points.txt
wva.egg-info/requires.txt
wva.egg-info/top_level.txt
wva/test/__init__.py
wva/test/test_core.py
wva/test/test_http_client.py
wva/test/test_stream.py
wva/test/test_subscriptions.py
wva/test/test_utilities.py
wva/test/test_vehicle.py