Metadata-Version: 1.1
Name: wva
Version: 0.1.0
Summary: Python API/CLI for the Digi Wireless Vehicle Adapter (WVA)
Home-page: https://github.com/digidotcom/python-wvalib
Author: Digi International Inc.
Author-email: paul.osborne@etherios.com
License: UNKNOWN
Platform: UNKNOWN
Classifier: Development Status :: 3 - Alpha
Classifier: Intended Audience :: Developers
Classifier: License :: OSI Approved :: Mozilla Public License 2.0 (MPL 2.0)
Classifier: Programming Language :: Python :: 2.7
Classifier: Programming Language :: Python :: 3
Classifier: Programming Language :: Python :: 3.2
Classifier: Programming Language :: Python :: 3.3
Classifier: Programming Language :: Python :: 3.4
Classifier: Topic :: Software Development :: Libraries
Classifier: Operating System :: OS Independent
